rateme/__init__.py
rateme/rateme.cfg
rateme/rateme.weights
rateme/utils.py
rateme-0.1.0.dist-info/METADATA
rateme-0.1.0.dist-info/RECORD
rateme-0.1.0.dist-info/WHEEL
rateme-0.1.0.dist-info/top_level.txt
