Metadata-Version: 2.1
Name: rateme
Version: 0.1.0
Summary: RateMe is a neural network that allows you to recognize gestures of thumb up and thumb down
Home-page: https://github.com/heyml/rateme
Maintainer: heyML
License: MIT
Platform: UNKNOWN
Classifier: Development Status :: 4 - Beta
Classifier: Environment :: Console
Classifier: Intended Audience :: Developers
Classifier: Intended Audience :: Education
Classifier: Intended Audience :: Information Technology
Classifier: Intended Audience :: Science/Research
Classifier: License :: OSI Approved :: MIT License
Classifier: Programming Language :: Python :: 3
Classifier: Programming Language :: C++
Classifier: Operating System :: POSIX :: Linux
Classifier: Topic :: Scientific/Engineering
Classifier: Topic :: Scientific/Engineering :: Image Recognition
Classifier: Topic :: Software Development
Requires-Dist: numpy
Requires-Dist: opencv-python
